barcode/__init__.py
barcode/base.py
barcode/codabar.py
barcode/codex.py
barcode/ean.py
barcode/errors.py
barcode/isxn.py
barcode/itf.py
barcode/pybarcode.py
barcode/upc.py
barcode/version.py
barcode/writer.py
barcode/charsets/__init__.py
barcode/charsets/codabar.py
barcode/charsets/code128.py
barcode/charsets/code39.py
barcode/charsets/ean.py
barcode/charsets/itf.py
barcode/charsets/upc.py
barcode/fonts/DejaVuSansMono.ttf
python_barcode-0.15.1.dist-info/LICENCE
python_barcode-0.15.1.dist-info/METADATA
python_barcode-0.15.1.dist-info/WHEEL
python_barcode-0.15.1.dist-info/entry_points.txt
python_barcode-0.15.1.dist-info/top_level.txt
python_barcode-0.15.1.dist-info/RECORD
