Metadata-Version: 2.1
Name: python-barcode
Version: 0.15.1
Summary: Create standard barcodes with Python. No external modules needed. (optional Pillow support included).
Home-page: https://github.com/WhyNotHugo/python-barcode
Author: Hugo Osvaldo Barrera et al
Author-email: hugo@barrera.io
License: MIT
Platform: UNKNOWN
Classifier: Development Status :: 5 - Production/Stable
Classifier: Environment :: Console
Classifier: Intended Audience :: Developers
Classifier: License :: OSI Approved :: MIT License
Classifier: Operating System :: OS Independent
Classifier: Programming Language :: Python
Classifier: Programming Language :: Python :: 3
Classifier: Programming Language :: Python :: 3.7
Classifier: Programming Language :: Python :: 3.8
Classifier: Programming Language :: Python :: 3.9
Classifier: Programming Language :: Python :: 3.10
Classifier: Programming Language :: Python :: 3.11
Classifier: Topic :: Multimedia :: Graphics
Classifier: Topic :: Software Development :: Libraries :: Python Modules
Provides-Extra: images
